Metadata-Version: 1.1
Name: aiotarantool-queue
Version: 0.0.3
Summary: Tarantool Queue python bindings for asyncio
Home-page: https://github.com/shveenkov/aiotarantool-queue-python
Author: Dmitry Shveenkov
Author-email: shveenkov@mail.ru
License: UNKNOWN
Platform: UNKNOWN
Classifier: Programming Language :: Python :: 3.4
Classifier: Intended Audience :: Developers
Classifier: License :: OSI Approved :: GNU Library or Lesser General Public License (LGPL)
Classifier: Operating System :: OS Independent
Classifier: Topic :: Software Development :: Libraries :: Python Modules
Classifier: Topic :: Database :: Front-Ends
